pysupwsdpocket/__init__.py
pysupwsdpocket/__main__.py
pysupwsdpocket/_version.py
pysupwsdpocket/pysupwsdpocket.py
pysupwsdpocket/supwsd-pocket.jar
pysupwsdpocket-0.0.7.dist-info/METADATA
pysupwsdpocket-0.0.7.dist-info/WHEEL
pysupwsdpocket-0.0.7.dist-info/entry_points.txt
pysupwsdpocket-0.0.7.dist-info/top_level.txt
pysupwsdpocket-0.0.7.dist-info/RECORD
