Metadata-Version: 2.1
Name: pysupwsdpocket
Version: 0.0.7
Summary: Just a Python Version of SupWSD Pocket: A software suite for SUPervised Word Sense Disambiguation
Home-page: https://github.com/rodriguesfas/PySupWSDPocket
Author: RodriguesFAS
Author-email: franciscosouzaacer@gmail.com
License: MIT
Keywords: natural-language-processing nlp natural-language-understanding supwsd wsd
Platform: UNKNOWN
Classifier: Development Status :: 3 - Alpha
Classifier: Intended Audience :: Developers
Classifier: Intended Audience :: Education
Classifier: Intended Audience :: Science/Research
Classifier: Intended Audience :: Information Technology
Classifier: Topic :: Scientific/Engineering
Classifier: Topic :: Scientific/Engineering :: Artificial Intelligence
Classifier: Topic :: Scientific/Engineering :: Information Analysis
Classifier: Topic :: Text Processing
Classifier: Topic :: Text Processing :: Linguistic
Classifier: Topic :: Software Development
Classifier: Topic :: Software Development :: Libraries
Classifier: Programming Language :: Python :: 3.7
Requires-Python: >=3.7
